lleaves/__init__.py
lleaves/data_processing.py
lleaves/lleaves.py
lleaves/llvm_binding.py
lleaves/compiler/__init__.py
lleaves/compiler/tree_compiler.py
lleaves/compiler/utils.py
lleaves/compiler/ast/__init__.py
lleaves/compiler/ast/nodes.py
lleaves/compiler/ast/parser.py
lleaves/compiler/ast/scanner.py
lleaves/compiler/codegen/__init__.py
lleaves/compiler/codegen/codegen.py
lleaves-1.3.0.dist-info/LICENSE
lleaves-1.3.0.dist-info/METADATA
lleaves-1.3.0.dist-info/WHEEL
lleaves-1.3.0.dist-info/top_level.txt
lleaves-1.3.0.dist-info/RECORD
