Metadata-Version: 2.1
Name: lleaves
Version: 1.3.0
Summary: LLVM-based compiler for LightGBM models
Home-page: https://github.com/siboehm/lleaves
Author: Simon Boehm
Author-email: simon@siboehm.com
License: MIT
Project-URL: Documentation, https://lleaves.readthedocs.io/en/latest/
Classifier: License :: OSI Approved :: MIT License
Classifier: Development Status :: 4 - Beta
Classifier: Programming Language :: Python :: 3
Requires-Python: >=3.7
License-File: LICENSE
Requires-Dist: llvmlite >=0.36
Requires-Dist: numpy
